temmies_cli/__init__.py
temmies_cli/cli.py
temmies_cli/commands/__init__.py
temmies_cli/commands/init.py
temmies_cli/commands/status.py
temmies_cli/commands/submit.py
temmies_cli/commands/utils.py
temmies_cli-1.0.121.dist-info/LICENSE
temmies_cli-1.0.121.dist-info/METADATA
temmies_cli-1.0.121.dist-info/WHEEL
temmies_cli-1.0.121.dist-info/entry_points.txt
temmies_cli-1.0.121.dist-info/top_level.txt
temmies_cli-1.0.121.dist-info/RECORD
