Metadata-Version: 2.1
Name: temmies-cli
Version: 1.0.121
Summary: A command-line tool for managing assignments using the Temmies library
Home-page: https://github.com/Code-For-Groningen/temmies-cli
Author: Boyan K.
Author-email: boyan@confest.im
License: GPLv3
Classifier: Development Status :: 4 - Beta
Classifier: Intended Audience :: Developers
Classifier: License :: OSI Approved :: GNU General Public License v3 (GPLv3)
Classifier: Programming Language :: Python :: 3.9
Classifier: Programming Language :: Python :: 3.10
Classifier: Programming Language :: Python :: 3.11
Requires-Python: >=3.9
License-File: LICENSE
Requires-Dist: click>=7.0
Requires-Dist: requests
Requires-Dist: lxml
Requires-Dist: keyring
Requires-Dist: temmies
Requires-Dist: tqdm
